{
  "type": "create:sequenced_assembly",
  "ingredient": {
    "item": "cobblemon_manufactory:white_ball_lid"
  },
  "results": [
    {
      "id": "cobblemon:premier_ball"
    }
  ],
  "sequence": [
    {
      "type": "create:deploying",
      "ingredients": [
        {
          "item": "cobblemon_manufactory:incomplete_premier_ball"
        },
        {
          "item": "cobblemon_manufactory:iron_ball_base"
        }
      ],
      "results": [
        {
          "id": "cobblemon_manufactory:incomplete_premier_ball"
        }
      ]
    },
    {
      "type": "create:deploying",
      "ingredients": [
        {
          "item": "cobblemon_manufactory:incomplete_premier_ball"
        },
        {
          "item": "create:copper_nugget"
        }
      ],
      "results": [
        {
          "id": "cobblemon_manufactory:incomplete_premier_ball"
        }
      ]
    }
  ],
  "transitional_item": {
    "id": "cobblemon_manufactory:incomplete_premier_ball"
  }
}